xd/__init__.py
xd/__main__.py
xd/__version__.py
xd/cmd_batch.py
xd/cmd_config.py
xd/cmd_gitinit.py
xd/cmd_watch.py
xd/helpers.py
xd/proc.py
xd-0.1.8.dist-info/LICENSE
xd-0.1.8.dist-info/METADATA
xd-0.1.8.dist-info/WHEEL
xd-0.1.8.dist-info/entry_points.txt
xd-0.1.8.dist-info/top_level.txt
xd-0.1.8.dist-info/RECORD
