Metadata-Version: 2.1
Name: xd
Version: 0.1.8
Summary: a list of useful commands which makes life easier
Home-page: https://github.com/damnever/xd
Author: damnever
Author-email: dxc.wolf@gmail.com
License: The BSD 3-Clause License
Keywords: command line tools
Platform: UNKNOWN
Classifier: Development Status :: 5 - Production/Stable
Classifier: Intended Audience :: Developers
Classifier: Topic :: Utilities
Classifier: License :: OSI Approved :: BSD License
Classifier: Programming Language :: Python :: 2.7
Classifier: Programming Language :: Python :: 3.2
Classifier: Programming Language :: Python :: 3.3
Classifier: Programming Language :: Python :: 3.4
Classifier: Programming Language :: Python :: 3.5
Classifier: Programming Language :: Python :: 3.6
License-File: LICENSE
Requires-Dist: colorama
Requires-Dist: click
Requires-Dist: requests
Requires-Dist: six (>=1.11.0)
Requires-Dist: pyyaml
Requires-Dist: pytoml
Requires-Dist: configparser
